[
  {
    "__type__": "cc.Prefab",
    "_name": "richtext",
    "_objFlags": 0,
    "_rawFiles": null,
    "data": {
      "__id__": 1
    },
    "asyncLoadAssets": false
  },
  {
    "__type__": "cc.Node",
    "_name": "richText",
    "_objFlags": 0,
    "_opacity": 255,
    "_color": {
      "__type__": "cc.Color",
      "r": 255,
      "g": 255,
      "b": 255,
      "a": 255
    },
    "_cascadeOpacityEnabled": true,
    "_parent": null,
    "_anchorPoint": {
      "__type__": "cc.Vec2",
      "x": 0.5,
      "y": 0.5
    },
    "_contentSize": {
      "__type__": "cc.Size",
      "width": 153.38,
      "height": 50
    },
    "_children": [],
    "_rotationX": 0,
    "_rotationY": 0,
    "_scaleX": 1,
    "_scaleY": 1,
    "_position": {
      "__type__": "cc.Vec2",
      "x": 0,
      "y": 0
    },
    "_skewX": 0,
    "_skewY": 0,
    "_localZOrder": 0,
    "_globalZOrder": 0,
    "_tag": -1,
    "_opacityModifyRGB": false,
    "_id": "",
    "_active": true,
    "_components": [
      {
        "__id__": 2
      }
    ],
    "_prefab": {
      "__id__": 3
    },
    "groupIndex": 0
  },
  {
    "__type__": "cc.RichText",
    "_name": "",
    "_objFlags": 0,
    "node": {
      "__id__": 1
    },
    "_enabled": true,
    "_useOriginalSize": true,
    "_N$string": "<color=#00ff00>Rich</c><color=#0fffff>Text</color>",
    "_N$horizontalAlign": 0,
    "_N$fontSize": 40,
    "_N$maxWidth": 0,
    "_N$lineHeight": 50
  },
  {
    "__type__": "cc.PrefabInfo",
    "root": {
      "__id__": 1
    },
    "asset": {
      "__uuid__": "4a37dd57-78cd-4cec-aad4-f11a73d12b63"
    },
    "fileId": "fd4fe1WoCpJK6rVCZ13Z14R"
  }
]